tr_news_scraper/__init__.py
tr_news_scraper/tr_news_scraper.py
tr_news_scraper-0.1.0.dist-info/METADATA
tr_news_scraper-0.1.0.dist-info/WHEEL
tr_news_scraper-0.1.0.dist-info/RECORD
