Metadata-Version: 2.1
Name: tr-news-scraper
Version: 0.1.0
Summary: tr-news-scraper is a Python library that allows users to scrape Turkish news articles based on specified keywords from multiple sources. It gather news content from various news websites, enabling users to extract valuable information for analysis or research purposes.
License: MIT
Author: Ogün Demir
Author-email: ogundemir8@gmail.com
Requires-Python: >=3.10,<4.0
Classifier: Development Status :: 5 - Production/Stable
Classifier: Intended Audience :: Developers
Classifier: License :: OSI Approved :: MIT License
Classifier: Operating System :: OS Independent
Classifier: Programming Language :: Python :: 3
Classifier: Programming Language :: Python :: 3.10
Classifier: Programming Language :: Python :: 3.11
Classifier: Programming Language :: Python :: 3.12
Classifier: Topic :: Software Development :: Libraries :: Python Modules
Requires-Dist: beautifulsoup4 (==4.12.2)
Requires-Dist: certifi (==2023.11.17)
Requires-Dist: charset-normalizer (==3.3.2)
Requires-Dist: click (==8.1.7)
Requires-Dist: cssselect (==1.2.0)
Requires-Dist: feedfinder2 (==0.0.4)
Requires-Dist: feedparser (==6.0.11)
Requires-Dist: filelock (==3.13.1)
Requires-Dist: idna (==3.6)
Requires-Dist: jieba3k (==0.35.1)
Requires-Dist: joblib (==1.3.2)
Requires-Dist: lxml (==5.1.0)
Requires-Dist: newspaper3k (==0.2.8)
Requires-Dist: nltk (==3.8.1)
Requires-Dist: numpy (==1.26.3)
Requires-Dist: pandas (==2.1.4)
Requires-Dist: pillow (==10.2.0)
Requires-Dist: python-dateutil (==2.8.2)
Requires-Dist: pytz (==2023.3.post1)
Requires-Dist: pyyaml (==6.0.1)
Requires-Dist: regex (==2023.12.25)
Requires-Dist: requests (==2.31.0)
Requires-Dist: requests-file (==1.5.1)
Requires-Dist: sgmllib3k (==1.0.0)
Requires-Dist: six (==1.16.0)
Requires-Dist: soupsieve (==2.5)
Requires-Dist: tinysegmenter (==0.3)
Requires-Dist: tldextract (==5.1.1)
Requires-Dist: tqdm (==4.66.1)
Requires-Dist: tzdata (==2023.4)
Requires-Dist: urllib3 (==2.1.0)
Project-URL: documentation, https://github.com/demirogun/tr-news-scraper/blob/main/README.md
Project-URL: github, https://github.com/demirogun/tr-news-scraper
Project-URL: homepage, https://github.com/demirogun/tr-news-scraper
Project-URL: issues, https://github.com/demirogun/tr-news-scraper/issues
Project-URL: repository, https://pypi.org/project/tr-news-scraper/
